pibot/__init__.py
pibot/background.py
pibot/buttons.py
pibot/camera.py
pibot/constants.py
pibot/lcd.py
pibot/leds.py
pibot/nano.py
pibot/serial_comm.py
pibot/startup.py
pibot/utils.py
pibot-76.dist-info/LICENSE
pibot-76.dist-info/METADATA
pibot-76.dist-info/WHEEL
pibot-76.dist-info/top_level.txt
pibot-76.dist-info/RECORD
